sec2time-1.2.0.dist-info/METADATA
sec2time-1.2.0.dist-info/WHEEL
sec2time/__init__.py
sec2time/sec2time.py
sec2time-1.2.0.dist-info/RECORD
